common_game_maths/Color.py
common_game_maths/Point.py
common_game_maths/Vector.py
common_game_maths/__init__.py
common_game_maths-1.0.3.dist-info/LICENSE
common_game_maths-1.0.3.dist-info/METADATA
common_game_maths-1.0.3.dist-info/WHEEL
common_game_maths-1.0.3.dist-info/top_level.txt
common_game_maths-1.0.3.dist-info/RECORD
